asyncnetfsm/__init__.py
asyncnetfsm/constants.py
asyncnetfsm/dispatcher.py
asyncnetfsm/exceptions.py
asyncnetfsm/logger.py
asyncnetfsm/utils.py
asyncnetfsm/version.py
asyncnetfsm/connections/__init__.py
asyncnetfsm/connections/base.py
asyncnetfsm/connections/interface.py
asyncnetfsm/connections/ssh.py
asyncnetfsm/connections/telnet.py
asyncnetfsm/vendors/__init__.py
asyncnetfsm/vendors/base.py
asyncnetfsm/vendors/comware_like.py
asyncnetfsm/vendors/ios_like.py
asyncnetfsm/vendors/junos_like.py
asyncnetfsm/vendors/arista/__init__.py
asyncnetfsm/vendors/arista/arista_eos.py
asyncnetfsm/vendors/aruba/__init__.py
asyncnetfsm/vendors/aruba/aruba_aos_6.py
asyncnetfsm/vendors/aruba/aruba_aos_8.py
asyncnetfsm/vendors/cisco/__init__.py
asyncnetfsm/vendors/cisco/cisco_asa.py
asyncnetfsm/vendors/cisco/cisco_ios.py
asyncnetfsm/vendors/cisco/cisco_iosxr.py
asyncnetfsm/vendors/cisco/cisco_nxos.py
asyncnetfsm/vendors/fujitsu/__init__.py
asyncnetfsm/vendors/fujitsu/fujitsu_switch.py
asyncnetfsm/vendors/hp/__init__.py
asyncnetfsm/vendors/hp/hp_comware.py
asyncnetfsm/vendors/hp/hp_comware_limited.py
asyncnetfsm/vendors/infotecs/HW1000.py
asyncnetfsm/vendors/infotecs/__init__.py
asyncnetfsm/vendors/juniper/__init__.py
asyncnetfsm/vendors/juniper/juniper_junos.py
asyncnetfsm/vendors/mikrotik/__init__.py
asyncnetfsm/vendors/mikrotik/mikrotik_routeros.py
asyncnetfsm/vendors/terminal/__init__.py
asyncnetfsm/vendors/terminal/terminal.py
asyncnetfsm/vendors/ubiquiti/__init__.py
asyncnetfsm/vendors/ubiquiti/ubiquity_edge.py
asyncnetfsm-0.0.11.dist-info/METADATA
asyncnetfsm-0.0.11.dist-info/WHEEL
asyncnetfsm-0.0.11.dist-info/top_level.txt
asyncnetfsm-0.0.11.dist-info/RECORD
