Metadata-Version: 2.1
Name: asyncnetfsm
Version: 0.0.11
Summary: simply its Netdev with textFSM 
Home-page: https://github.com/omaralghussein/asyncnetfsm
Author: Omar Al-Ghussein
Author-email: z3@live.it
License: UNKNOWN
Platform: UNKNOWN
Classifier: Programming Language :: Python :: 3
Classifier: License :: OSI Approved :: MIT License
Classifier: Operating System :: OS Independent
Requires-Python: >=3.6
